[
  {
    "title": "Javascript is cool!",
    "content": "With javascript, you can do anything you want to a website!  Its the best coding language.",
    "user_id": 5
  },
  {
    "title": "I ",
    "content": "With javascript, you can do anything you want to a website!  Its the best coding language.",
    "user_id": 5
  },
    {
    "title": "Javascript is cool!",
    "content": "With javascript, you can do anything you want to a website!  Its the best coding language.",
    "user_id": 5
  },
    {
    "title": "Javascript is cool!",
    "content": "With javascript, you can do anything you want to a website!  Its the best coding language.",
    "user_id": 5
  },
    {
    "title": "Javascript is cool!",
    "content": "With javascript, you can do anything you want to a website!  Its the best coding language.",
    "user_id": 5
  },
    {
    "title": "Javascript is cool!",
    "content": "With javascript, you can do anything you want to a website!  Its the best coding language.",
    "user_id": 5
  },
    {
    "title": "Javascript is cool!",
    "content": "With javascript, you can do anything you want to a website!  Its the best coding language.",
    "user_id": 5
  }
]
